freeai/__init__.py
freeai/main.py
freechat-1.0.0.dist-info/METADATA
freechat-1.0.0.dist-info/WHEEL
freechat-1.0.0.dist-info/top_level.txt
freechat-1.0.0.dist-info/RECORD
