Metadata-Version: 2.1
Name: freechat
Version: 1.0.0
Summary: A package allowing you to use multiple AI Modals for free!
Author: Cannonball Chris
Author-email: cannonballchris8@gmail.com
Keywords: freegpt,gpt,ai,free,freetech
Classifier: Development Status :: 1 - Planning
Classifier: Intended Audience :: Developers
Classifier: Programming Language :: Python :: 3
Classifier: Operating System :: Unix
Classifier: Operating System :: MacOS :: MacOS X
Classifier: Operating System :: Microsoft :: Windows
Requires-Dist: aiohttp
